num6/Num6.py
num6/__init__.py
num6/__main__.py
num6/charlib.py
num6/cli.py
num6/num6_gui.py
num6/packages.py
Num6-0.4.0.dist-info/LICENSE
Num6-0.4.0.dist-info/METADATA
Num6-0.4.0.dist-info/WHEEL
Num6-0.4.0.dist-info/entry_points.txt
Num6-0.4.0.dist-info/top_level.txt
Num6-0.4.0.dist-info/RECORD
