Metadata-Version: 2.1
Name: Num6
Version: 0.4.0
Summary: Num6 - An cryptography tool for Python 3 (open source).
Home-page: https://github.com/almas-ali/num6
Author: Md. Almas Ali
Author-email: almaspr3@gmail.com
License: MIT
Platform: UNKNOWN
Classifier: Development Status :: 4 - Beta
Classifier: Operating System :: OS Independent
Classifier: Intended Audience :: Developers
Classifier: License :: OSI Approved :: MIT License
Classifier: Programming Language :: Python :: 3
Classifier: Topic :: Security :: Cryptography
Classifier: Natural Language :: English
Classifier: Environment :: Console
License-File: LICENSE
